[
  {
    "constructorYn": true,
    "title": "RedRenderer",
    "description": "\n    RedRenderer 인스턴스 생성자.\n",
    "return": "RedRenderer Instance"
  },
  {
    "code": "FUNCTION",
    "title": "start",
    "description": "\n    렌더 시작\n",
    "params": {
      "gl": [
        {
          "type": "webgl context"
        },
        "webgl context"
      ]
    },
    "return": "void"
  },
  {
    "code": "FUNCTION",
    "title": "stop",
    "description": "\n    렌더 중지\n",
    "return": "void"
  },
  {
    "code": "FUNCTION",
    "title": "worldRender",
    "description": "\n    등록된 RedView을 기반으로 렌더링을 실행함\n",
    "params": {
      "gl": [
        {
          "type": "webgl context"
        },
        "webgl context"
      ]
    },
    "return": "void"
  }
]