[
  {
    "code": "PROPERTY",
    "title": "alpha",
    "description": "기본값 : 1",
    "return": "Number"
  },
  {
    "code": "PROPERTY",
    "title": "cutOff",
    "description": "기본값 : 0",
    "return": "Number"
  },
  {
    "code": "PROPERTY",
    "title": "diffuseTexture",
    "description": "diffuseTexture",
    "return": "RedBitmapTexture"
  },
  {
    "code": "PROPERTY",
    "title": "emissiveFactor",
    "description": "기본값 : 1",
    "return": "Number"
  },
  {
    "code": "PROPERTY",
    "title": "emissiveTexture",
    "description": "emissiveTexture",
    "return": "RedBitmapTexture"
  },
  {
    "code": "PROPERTY",
    "title": "environmentTexture",
    "description": "environmentTexture",
    "return": "RedBitmapCubeTexture"
  },
  {
    "code": "PROPERTY",
    "title": "metallicFactor",
    "description": "기본값 : 1",
    "return": "Number"
  },
  {
    "code": "PROPERTY",
    "title": "normalPower",
    "description": "기본값 : 1",
    "return": "number"
  },
  {
    "code": "PROPERTY",
    "title": "normalTexture",
    "description": "normalTexture",
    "return": "RedBitmapTexture"
  },
  {
    "code": "PROPERTY",
    "title": "occlusionPower",
    "description": "기본값 : 1",
    "return": "Number"
  },
  {
    "code": "PROPERTY",
    "title": "occlusionTexture",
    "description": "occlusionTexture",
    "return": "RedBitmapTexture"
  },
  {
    "constructorYn": true,
    "title": "RedPBRMaterial",
    "description": "\n\t RedPBRMaterial Instance 생성\n ",
    "params": {
      "redGL": [
        {
          "type": "RedGL"
        }
      ],
      "diffuseTexture": [
        {
          "type": "RedBitmapTexture"
        }
      ],
      "environmentTexture": [
        {
          "type": "RedBitmapCubeTexture"
        }
      ],
      "normalTexture": [
        {
          "type": "RedBitmapTexture"
        }
      ],
      "occlusionTexture": [
        {
          "type": "RedBitmapTexture"
        }
      ],
      "emissiveTexture": [
        {
          "type": "RedBitmapTexture"
        }
      ],
      "roughnessTexture": [
        {
          "type": "RedBitmapTexture"
        }
      ]
    },
    "extends": [
      "RedBaseMaterial"
    ],
    "demo": "../example/material/RedPBRMaterial.html",
    "example": "\n\t RedPBRMaterial(\n\t\t RedGL Instance,\n\t\t RedBitmapTexture(RedGL Instance, src), // diffuseTexture\n\t\t RedBitmapCubeTexture(RedGL Instance, srcList),\n\t\t RedBitmapTexture(RedGL Instance, src), // normalTexture\n\t\t RedBitmapTexture(RedGL Instance, src), // occlusionTexture\n\t\t RedBitmapTexture(RedGL Instance, src), // emissiveTexture\n\t\t RedBitmapTexture(RedGL Instance, src) // roughnessTexture\n\t )\n ",
    "return": "RedPBRMaterial Instance"
  },
  {
    "code": "PROPERTY",
    "title": "roughnessFactor",
    "description": "기본값 : 0.1",
    "return": "Number"
  },
  {
    "code": "PROPERTY",
    "title": "roughnessTexture",
    "description": "roughnessTexture",
    "return": "RedBitmapTexture"
  },
  {
    "code": "PROPERTY",
    "title": "specularPower",
    "description": "기본값 : 1",
    "return": "Number"
  },
  {
    "code": "PROPERTY",
    "title": "useFlatMode",
    "description": "\n    flatMode 사용여부\n    기본값 : true\n ",
    "return": "boolean"
  },
  {
    "code": "PROPERTY",
    "title": "usePreMultiply",
    "description": "\n    usePreMultiply 사용여부\n    기본값 : false\n ",
    "return": "boolean"
  }
]